<?xml version="1.0" encoding="utf-8"?>
<scripts version="2.0">
	<script>
		<name>NetworkOutputs-Source</name>
		<file>C:\Temp\WHHT LogMeIn Scripts\Source\NetworkOutputs-Source.cmd</file>
		<resource></resource>
		<platforms>00000001</platforms>
		<autoexec>true</autoexec>
	</script>
	<script>
		<name>Check all windows updates</name>
		<file>C:\Temp\WHHT LogMeIn Scripts\Source\Check all windows updates.cmd</file>
		<resource></resource>
		<platforms>00000001</platforms>
		<autoexec>false</autoexec>
	</script>
	<script>
		<name>Check Windows Version</name>
		<file>C:\Temp\WHHT LogMeIn Scripts\Source\Check Windows Version.cmd</file>
		<resource></resource>
		<platforms>00000001</platforms>
		<autoexec>false</autoexec>
	</script>
	<script>
		<name>Clear DNS cache</name>
		<file>C:\Temp\WHHT LogMeIn Scripts\Source\Clear DNS cache.cmd</file>
		<resource></resource>
		<platforms>00000001</platforms>
		<autoexec>false</autoexec>
	</script>
	<script>
		<name>Collect all computer infomration</name>
		<file>C:\Temp\WHHT LogMeIn Scripts\Source\Collect all computer infomration .cmd</file>
		<resource></resource>
		<platforms>00000001</platforms>
		<autoexec>false</autoexec>
	</script>
	<script>
		<name>Collect all IP information</name>
		<file>C:\Temp\WHHT LogMeIn Scripts\Source\Collect all IP information.cmd</file>
		<resource></resource>
		<platforms>00000001</platforms>
		<autoexec>true</autoexec>
	</script>
	<script>
		<name>Collect applied policies to the user</name>
		<file>C:\Temp\WHHT LogMeIn Scripts\Source\Collect applied policies to the user.cmd</file>
		<resource></resource>
		<platforms>00000001</platforms>
		<autoexec>false</autoexec>
	</script>
	<script>
		<name>Collect the asset generation</name>
		<file>C:\Temp\WHHT LogMeIn Scripts\Source\Collect the asset generation.cmd</file>
		<resource></resource>
		<platforms>00000001</platforms>
		<autoexec>false</autoexec>
	</script>
	<script>
		<name>Collect the list of installed software</name>
		<file>C:\Temp\WHHT LogMeIn Scripts\Source\Collect the list of installed software.cmd</file>
		<resource></resource>
		<platforms>00000001</platforms>
		<autoexec>false</autoexec>
	</script>
	<script>
		<name>Collect the Username and the Asset number</name>
		<file>C:\Temp\WHHT LogMeIn Scripts\Source\Collect the Username and the Asset number .cmd</file>
		<resource></resource>
		<platforms>00000001</platforms>
		<autoexec>true</autoexec>
	</script>
	<script>
		<name>Collect Total Ram memory</name>
		<file>C:\Temp\WHHT LogMeIn Scripts\Source\Collect Total Ram memory.cmd</file>
		<resource></resource>
		<platforms>00000001</platforms>
		<autoexec>false</autoexec>
	</script>
	<script>
		<name>Delete Teams App data</name>
		<file>C:\Temp\WHHT LogMeIn Scripts\Source\Delete Teams App data.cmd</file>
		<resource></resource>
		<platforms>00000001</platforms>
		<autoexec>false</autoexec>
	</script>
	<script>
		<name>Get all the installed drivers</name>
		<file>C:\Temp\WHHT LogMeIn Scripts\Source\Get all the installed drivers.cmd</file>
		<resource></resource>
		<platforms>00000001</platforms>
		<autoexec>false</autoexec>
	</script>
	<script>
		<name>Open Outlook profiles</name>
		<file>C:\Temp\WHHT LogMeIn Scripts\Source\Open Outlook profiles.cmd</file>
		<resource></resource>
		<platforms>00000001</platforms>
		<autoexec>false</autoexec>
	</script>
	<script>
		<name>Open task manager</name>
		<file>C:\Temp\WHHT LogMeIn Scripts\Source\Open task manager.cmd</file>
		<resource></resource>
		<platforms>00000001</platforms>
		<autoexec>false</autoexec>
	</script>
	<script>
		<name>Remove the web credentials</name>
		<file>C:\Temp\WHHT LogMeIn Scripts\Source\Remove the web credentials.cmd</file>
		<resource></resource>
		<platforms>00000001</platforms>
		<autoexec>false</autoexec>
	</script>
	<script>
		<name>Reset Internet explorer settings.</name>
		<file>C:\Temp\WHHT LogMeIn Scripts\Source\Reset Internet explorer settings.cmd</file>
		<resource></resource>
		<platforms>00000001</platforms>
		<autoexec>false</autoexec>
	</script>
	<script>
		<name>Restart the computer</name>
		<file>C:\Temp\WHHT LogMeIn Scripts\Source\Restart the computer.cmd</file>
		<resource></resource>
		<platforms>00000001</platforms>
		<autoexec>false</autoexec>
	</script>
	<script>
		<name>The computer boot time</name>
		<file>C:\Temp\WHHT LogMeIn Scripts\Source\The computer boot time.cmd</file>
		<resource></resource>
		<platforms>00000001</platforms>
		<autoexec>false</autoexec>
	</script>
	<script>
		<name>Update group policy</name>
		<file>C:\Temp\WHHT LogMeIn Scripts\Source\Update group policy .cmd</file>
		<resource></resource>
		<platforms>00000001</platforms>
		<autoexec>false</autoexec>
	</script>
</scripts>
